Workbook

Sheet Budget
A1: Year | B1: Month | C1: Entity | D1: Department | E1: Account | F1: Budget_Amount
A2: 2024 | B2: 1 | C2: INDIA | D2: Finance | E2: Revenue | F2: 309524.4
A3: 2024 | B3: 1 | C3: INDIA | D3: Finance | E3: COGS | F3: 196867
A4: 2024 | B4: 1 | C4: INDIA | D4: Finance | E4: Salary Expense | F4: 181932
A5: 2024 | B5: 1 | C5: INDIA | D5: Finance | E5: IT Infrastructure | F5: 153694
A6: 2024 | B6: 1 | C6: INDIA | D6: Finance | E6: Marketing Expense | F6: 169879
A7: 2024 | B7: 1 | C7: INDIA | D7: IT | E7: Revenue | F7: 288482.4
A8: 2024 | B8: 1 | C8: INDIA | D8: IT | E8: COGS | F8: 104886
A9: 2024 | B9: 1 | C9: INDIA | D9: IT | E9: Salary Expense | F9: 187337
A10: 2024 | B10: 1 | C10: INDIA | D10: IT | E10: IT Infrastructure | F10: 137498
A11: 2024 | B11: 1 | C11: INDIA | D11: IT | E11: Marketing Expense | F11: 162727
A12: 2024 | B12: 1 | C12: INDIA | D12: Sales | E12: Revenue | F12: 317383.2
A13: 2024 | B13: 1 | C13: INDIA | D13: Sales | E13: COGS | F13: 66023
... A1441: 2025 | B1441: 12 | C1441: UK | D1441: HR | E1441: Marketing Expense | F1441: 71563

Sheet Actuals
A1: Year | B1: Month | C1: Entity | D1: Department | E1: Account | F1: Actual_Amount
A2: 2024 | B2: 1 | C2: INDIA | D2: Finance | E2: Revenue | F2: 284883
A3: 2024 | B3: 1 | C3: INDIA | D3: Finance | E3: COGS | F3: 185960
A4: 2024 | B4: 1 | C4: INDIA | D4: Finance | E4: Salary Expense | F4: 209160
A5: 2024 | B5: 1 | C5: INDIA | D5: Finance | E5: IT Infrastructure | F5: 147052
A6: 2024 | B6: 1 | C6: INDIA | D6: Finance | E6: Marketing Expense | F6: 135031
A7: 2024 | B7: 1 | C7: INDIA | D7: IT | E7: Revenue | F7: 242718
A8: 2024 | B8: 1 | C8: INDIA | D8: IT | E8: COGS | F8: 182212
A9: 2024 | B9: 1 | C9: INDIA | D9: IT | E9: Salary Expense | F9: 107488
A10: 2024 | B10: 1 | C10: INDIA | D10: IT | E10: IT Infrastructure | F10: 94917
A11: 2024 | B11: 1 | C11: INDIA | D11: IT | E11: Marketing Expense | F11: 222520
A12: 2024 | B12: 1 | C12: INDIA | D12: Sales | E12: Revenue | F12: 332367
A13: 2024 | B13: 1 | C13: INDIA | D13: Sales | E13: COGS | F13: 52188
... A1441: 2025 | B1441: 12 | C1441: UK | D1441: HR | E1441: Marketing Expense | F1441: 129973

Sheet Forecast
A1: Year | B1: Month | C1: Entity | D1: Department | E1: Account | F1: Forecast_Amount
A2: 2024 | B2: 1 | C2: INDIA | D2: Finance | E2: Revenue | F2: 342040
A3: 2024 | B3: 1 | C3: INDIA | D3: Finance | E3: COGS | F3: 166762
A4: 2024 | B4: 1 | C4: INDIA | D4: Finance | E4: Salary Expense | F4: 89886
A5: 2024 | B5: 1 | C5: INDIA | D5: Finance | E5: IT Infrastructure | F5: 127787
A6: 2024 | B6: 1 | C6: INDIA | D6: Finance | E6: Marketing Expense | F6: 61959
A7: 2024 | B7: 1 | C7: INDIA | D7: IT | E7: Revenue | F7: 306694
A8: 2024 | B8: 1 | C8: INDIA | D8: IT | E8: COGS | F8: 185376
A9: 2024 | B9: 1 | C9: INDIA | D9: IT | E9: Salary Expense | F9: 59851
A10: 2024 | B10: 1 | C10: INDIA | D10: IT | E10: IT Infrastructure | F10: 156738
A11: 2024 | B11: 1 | C11: INDIA | D11: IT | E11: Marketing Expense | F11: 157925
A12: 2024 | B12: 1 | C12: INDIA | D12: Sales | E12: Revenue | F12: 227074
A13: 2024 | B13: 1 | C13: INDIA | D13: Sales | E13: COGS | F13: 215372
... A1441: 2025 | B1441: 12 | C1441: UK | D1441: HR | E1441: Marketing Expense | F1441: 117095

Sheet Account_Dimension
A1: Account | B1: Account_Type
A2: Revenue | B2: Revenue
A3: COGS | B3: Expense
A4: Salary Expense | B4: Expense
A5: IT Infrastructure | B5: Expense
A6: Marketing Expense | B6: Expense

Sheet Entity_Dimension
A1: Entity | B1: Region
A2: INDIA | B2: APAC
A3: US | B3: NA
A4: UK | B4: EMEA

Sheet BudgetvsActual_Analysis
A1: Year | B1: Month | C1: Entity | D1: Department | E1: Account | F1: Actual_Amount | G1: Budget_Amount | H1: Variance % | I1: Forecast Accuracy %
A2: 2024 | B2: 1 | C2: INDIA | D2: Finance | E2: Revenue | F2: 284883 | G2: 309524.4 | H2: =(F2-G2)/G2 -> -0.079610525 | I2: =1-ABS(F2-Forecast!F2)/F2 -> 0.79936676
A3: 2024 | B3: 1 | C3: INDIA | D3: Finance | E3: COGS | F3: 185960 | G3: 196867 | H3: =(F3-G3)/G3 -> -0.055402886 | I3: =1-ABS(F3-Forecast!F3)/F3 -> 0.89676274
A4: 2024 | B4: 1 | C4: INDIA | D4: Finance | E4: Salary Expense | F4: 209160 | G4: 181932 | H4: =(F4-G4)/G4 -> 0.14966031 | I4: =1-ABS(F4-Forecast!F4)/F4 -> 0.42974756
A5: 2024 | B5: 1 | C5: INDIA | D5: Finance | E5: IT Infrastructure | F5: 147052 | G5: 153694 | H5: =(F5-G5)/G5 -> -0.04321574 | I5: =1-ABS(F5-Forecast!F5)/F5 -> 0.86899192
A6: 2024 | B6: 1 | C6: INDIA | D6: Finance | E6: Marketing Expense | F6: 135031 | G6: 169879 | H6: =(F6-G6)/G6 -> -0.20513424 | I6: =1-ABS(F6-Forecast!F6)/F6 -> 0.45885019
A7: 2024 | B7: 1 | C7: INDIA | D7: IT | E7: Revenue | F7: 242718 | G7: 288482.4 | H7: =(F7-G7)/G7 -> -0.15863845 | I7: =1-ABS(F7-Forecast!F7)/F7 -> 0.7364184
A8: 2024 | B8: 1 | C8: INDIA | D8: IT | E8: COGS | F8: 182212 | G8: 104886 | H8: =(F8-G8)/G8 -> 0.73723853 | I8: =1-ABS(F8-Forecast!F8)/F8 -> 0.98263561
A9: 2024 | B9: 1 | C9: INDIA | D9: IT | E9: Salary Expense | F9: 107488 | G9: 187337 | H9: =(F9-G9)/G9 -> -0.42623187 | I9: =1-ABS(F9-Forecast!F9)/F9 -> 0.55681564
A10: 2024 | B10: 1 | C10: INDIA | D10: IT | E10: IT Infrastructure | F10: 94917 | G10: 137498 | H10: =(F10-G10)/G10 -> -0.3096845 | I10: =1-ABS(F10-Forecast!F10)/F10 -> 0.34868359 | O10: >95% → very good forecasting
A11: 2024 | B11: 1 | C11: INDIA | D11: IT | E11: Marketing Expense | F11: 222520 | G11: 162727 | H11: =(F11-G11)/G11 -> 0.36744363 | I11: =1-ABS(F11-Forecast!F11)/F11 -> 0.70971149
A12: 2024 | B12: 1 | C12: INDIA | D12: Sales | E12: Revenue | F12: 332367 | G12: 317383.2 | H12: =(F12-G12)/G12 -> 0.047210438 | I12: =1-ABS(F12-Forecast!F12)/F12 -> 0.6832026 | O12: 85–95% → acceptable
A13: 2024 | B13: 1 | C13: INDIA | D13: Sales | E13: COGS | F13: 52188 | G13: 66023 | H13: =(F13-G13)/G13 -> -0.20954819 | I13: =1-ABS(F13-Forecast!F13)/F13 -> -2.1268491
A14: 2024 | B14: 1 | C14: INDIA | D14: Sales | E14: Salary Expense | F14: 107854 | G14: 91090 | H14: =(F14-G14)/G14 -> 0.18403776 | I14: =1-ABS(F14-Forecast!F14)/F14 -> 0.79504701 | O14: <85% → needs improvement
A15: 2024 | B15: 1 | C15: INDIA | D15: Sales | E15: IT Infrastructure | F15: 99686 | G15: 117221 | H15: =(F15-G15)/G15 -> -0.14958924 | I15: =1-ABS(F15-Forecast!F15)/F15 -> 0.69852336
A16: 2024 | B16: 1 | C16: INDIA | D16: Sales | E16: Marketing Expense | F16: 61655 | G16: 114820 | H16: =(F16-G16)/G16 -> -0.46302909 | I16: =1-ABS(F16-Forecast!F16)/F16 -> 0.16872922
A17: 2024 | B17: 1 | C17: INDIA | D17: HR | E17: Revenue | F17: 132934 | G17: 91384.2 | H17: =(F17-G17)/G17 -> 0.4546716 | I17: =1-ABS(F17-Forecast!F17)/F17 -> 0.64069388
A18: 2024 | B18: 1 | C18: INDIA | D18: HR | E18: COGS | F18: 137358 | G18: 109735 | H18: =(F18-G18)/G18 -> 0.25172461 | I18: =1-ABS(F18-Forecast!F18)/F18 -> 0.67622563
A19: 2024 | B19: 1 | C19: INDIA | D19: HR | E19: Salary Expense | F19: 96601 | G19: 114925 | H19: =(F19-G19)/G19 -> -0.15944312 | I19: =1-ABS(F19-Forecast!F19)/F19 -> 0.66585232
A20: 2024 | B20: 1 | C20: INDIA | D20: HR | E20: IT Infrastructure | F20: 61093 | G20: 55311 | H20: =(F20-G20)/G20 -> 0.10453617 | I20: =1-ABS(F20-Forecast!F20)/F20 -> -0.3559655
A21: 2024 | B21: 1 | C21: INDIA | D21: HR | E21: Marketing Expense | F21: 166227 | G21: 153355 | H21: =(F21-G21)/G21 -> 0.083935966 | I21: =1-ABS(F21-Forecast!F21)/F21 -> 0.94134527
A22: 2024 | B22: 1 | C22: US | D22: Finance | E22: Revenue | F22: 190593 | G22: 243549 | H22: =(F22-G22)/G22 -> -0.21743468 | I22: =1-ABS(F22-Forecast!F22)/F22 -> 0.69758596
A23: 2024 | B23: 1 | C23: US | D23: Finance | E23: COGS | F23: 125295 | G23: 180608 | H23: =(F23-G23)/G23 -> -0.30625997 | I23: =1-ABS(F23-Forecast!F23)/F23 -> 0.72755497
A24: 2024 | B24: 1 | C24: US | D24: Finance | E24: Salary Expense | F24: 167003 | G24: 134478 | H24: =(F24-G24)/G24 -> 0.24186112 | I24: =1-ABS(F24-Forecast!F24)/F24 -> 0.48562601
A25: 2024 | B25: 1 | C25: US | D25: Finance | E25: IT Infrastructure | F25: 58041 | G25: 172537 | H25: =(F25-G25)/G25 -> -0.66360259 | I25: =1-ABS(F25-Forecast!F25)/F25 -> 0.1655037
A26: 2024 | B26: 1 | C26: US | D26: Finance | E26: Marketing Expense | F26: 112632 | G26: 199503 | H26: =(F26-G26)/G26 -> -0.43543706 | I26: =1-ABS(F26-Forecast!F26)/F26 -> 0.50957099
... A1441: 2025 | B1441: 12 | C1441: UK | D1441: HR | E1441: Marketing Expense | F1441: 129973 | G1441: 71563 | H1441: =(F1441-G1441)/G1441 -> 0.8162039 | I1441: =1-ABS(F1441-Forecast!F1441)/F1441 -> 0.90091788

Sheet YTD Actual
A3: Sum of Actual_Amount | B3: Column Labels
A4: Row Labels | B4: 1 | C4: 2 | D4: 3 | E4: 4 | F4: 5 | G4: 6 | H4: 7 | I4: 8 | J4: 9 | K4: 10 | L4: 11 | M4: 12 | N4: Grand Total
A5: INDIA | B5: 5984199 | C5: 12198103 | D5: 18159194 | E5: 24258705 | F5: 29914025 | G5: 36505908 | H5: 41995512 | I5: 47774468 | J5: 53491166 | K5: 59356656 | L5: 65952034 | M5: 71804150
A6: Finance | B6: 1814840 | C6: 3037285 | D6: 4424233 | E6: 5962896 | F6: 7340986 | G6: 8936698 | H6: 9943968 | I6: 11460945 | J6: 13016017 | K6: 14396102 | L6: 16058216 | M6: 17606067
A7: COGS | B7: 408576 | C7: 614053 | D7: 787400 | E7: 1016175 | F7: 1274549 | G7: 1454734 | H7: 1696767 | I7: 1908898 | J7: 2126511 | K7: 2342865 | L7: 2677473 | M7: 2968864
A8: IT Infrastructure | B8: 287896 | C8: 500138 | D8: 737949 | E8: 1015285 | F8: 1383336 | G8: 1631797 | H8: 1756751 | I8: 1965239 | J8: 2114727 | K8: 2401479 | L8: 2628642 | M8: 2848218
A9: Marketing Expense | B9: 196839 | C9: 470359 | D9: 610294 | E9: 890692 | F9: 1084753 | G9: 1311952 | H9: 1522705 | I9: 1866632 | J9: 2181694 | K9: 2377753 | L9: 2688447 | M9: 2964792
A10: Revenue | B10: 560937 | C10: 896391 | D10: 1465867 | E10: 1920104 | F10: 2132160 | G10: 2764291 | H10: 3009712 | I10: 3474438 | J10: 4095004 | K10: 4584704 | L10: 4988953 | M10: 5411801
A11: Salary Expense | B11: 360592 | C11: 556344 | D11: 822723 | E11: 1120640 | F11: 1466188 | G11: 1773924 | H11: 1958033 | I11: 2245738 | J11: 2498081 | K11: 2689301 | L11: 3074701 | M11: 3412392
A12: HR | B12: 1338697 | C12: 2645222 | D12: 4222052 | E12: 5781544 | F12: 7383144 | G12: 8873601 | H12: 10436261 | I12: 11656085 | J12: 13215807 | K12: 14648521 | L12: 16202221 | M12: 17564328
A13: COGS | B13: 195850 | C13: 415520 | D13: 678690 | E13: 934495 | F13: 1192250 | G13: 1446909 | H13: 1655078 | I13: 1996910 | J13: 2281232 | K13: 2516805 | L13: 2676456 | M13: 2853231
A14: IT Infrastructure | B14: 185334 | C14: 467170 | D14: 696594 | E14: 836802 | F14: 1211371 | G14: 1409977 | H14: 1586396 | I14: 1773195 | J14: 2030381 | K14: 2330984 | L14: 2707699 | M14: 2906475
A15: Marketing Expense | B15: 299115 | C15: 443172 | D15: 812187 | E15: 1155019 | F15: 1488255 | G15: 1655547 | H15: 1945140 | I15: 2078374 | J15: 2341969 | K15: 2486769 | L15: 2724732 | M15: 2988293
A16: Revenue | B16: 398242 | C16: 832139 | D16: 1348765 | E16: 1870654 | F16: 2336434 | G16: 2976275 | H16: 3616398 | I16: 3835733 | J16: 4309433 | K16: 4724819 | L16: 5180385 | M16: 5661261
... A80: Grand Total | B80: 17800544 | C80: 36382720 | D80: 54295421 | E80: 71772533 | F80: 88805783 | G80: 107190242 | H80: 124573924 | I80: 142020062 | J80: 159108934 | K80: 176927524 | L80: 195663033 | M80: 213114667

Sheet Budget vs Actual Summary
B3: Column Labels
B4: COGS | E4: IT Infrastructure | H4: Marketing Expense | K4: Revenue | N4: Salary Expense | Q4: Total Sum of Budget_Amount | R4: Total Sum of Actual_Amount | S4: Total Sum of Variance %
A5: Row Labels | B5: Sum of Budget_Amount | C5: Sum of Actual_Amount | D5: Sum of Variance % | E5: Sum of Budget_Amount | F5: Sum of Actual_Amount | G5: Sum of Variance % | H5: Sum of Budget_Amount | I5: Sum of Actual_Amount | J5: Sum of Variance % | K5: Sum of Budget_Amount | L5: Sum of Actual_Amount | M5: Sum of Variance % | N5: Sum of Budget_Amount | O5: Sum of Actual_Amount | P5: Sum of Variance %
A6: INDIA | B6: 12832127 | C6: 12165454 | D6: 7.0923173 | E6: 11852721 | F6: 11893291 | G6: 15.685692 | H6: 11865745 | I6: 12487100 | J6: 20.489365 | K6: 21440722 | L6: 22236788 | M6: 21.862189 | N6: 12514324 | O6: 13021517 | P6: 19.244663 | Q6: 70505639 | R6: 71804150 | S6: 84.374227
A7: Finance | B7: 3464758 | C7: 2968864 | D7: -1.8024368 | E7: 2956798 | F7: 2848218 | G7: 1.4582291 | H7: 3003047 | I7: 2964792 | J7: 2.3369416 | K7: 5821419.6 | L7: 5411801 | M7: 1.0671429 | N7: 3295121 | O7: 3412392 | P7: 3.8008751 | Q7: 18541144 | R7: 17606067 | S7: 6.860752
A8: HR | B8: 3068792 | C8: 2853231 | D8: 1.3129075 | E8: 3058448 | F8: 2906475 | G8: 1.4985355 | H8: 3080084 | I8: 2988293 | J8: 1.9689805 | K8: 5490779.4 | L8: 5661261 | M8: 6.4456563 | N8: 3015522 | O8: 3155068 | P8: 7.1213067 | Q8: 17713625 | R8: 17564328 | S8: 18.347386
A9: IT | B9: 3272358 | C9: 3176037 | D9: 2.3235444 | E9: 2824527 | F9: 3117695 | G9: 8.172762 | H9: 2990520 | I9: 3227440 | J9: 6.2066481 | K9: 5144448.6 | L9: 6079641 | M9: 10.391634 | N9: 3182330 | O9: 3123683 | P9: 4.1912654 | Q9: 17414184 | R9: 18724496 | S9: 31.285854
A10: Sales | B10: 3026219 | C10: 3167322 | D10: 5.2583022 | E10: 3012948 | F10: 3020903 | G10: 4.5561657 | H10: 2792094 | I10: 3306575 | J10: 9.976795 | K10: 4984074 | L10: 5084085 | M10: 3.9577558 | N10: 3021351 | O10: 3330374 | P10: 4.131216 | Q10: 16836686 | R10: 17909259 | S10: 27.880235
A11: UK | B11: 12086868 | C11: 11564918 | D11: 12.038166 | E11: 11910532 | F11: 12404861 | G11: 21.820773 | H11: 11793544 | I11: 11926123 | J11: 17.693903 | K11: 21593797 | L11: 21829846 | M11: 15.229014 | N11: 12508794 | O11: 12287070 | P11: 13.332237 | Q11: 69893535 | R11: 70012818 | S11: 80.114092
A12: Finance | B12: 3177784 | C12: 2921935 | D12: 0.15122007 | E12: 2807447 | F12: 3422739 | G12: 9.5921918 | H12: 2931002 | I12: 3176558 | J12: 6.7758783 | K12: 5626078.2 | L12: 5661772 | M12: 2.9837528 | N12: 2959675 | O12: 2900387 | P12: 4.1724386 | Q12: 17501986 | R12: 18083391 | S12: 23.675481
A13: HR | B13: 2664120 | C13: 2910547 | D13: 7.8718441 | E13: 3040135 | F13: 3102313 | G13: 4.0046436 | H13: 3137393 | I13: 3305566 | J13: 6.4517277 | K13: 5112972 | L13: 5119227 | M13: 2.2660793 | N13: 3145355 | O13: 3087143 | P13: 4.1144157 | Q13: 17099975 | R13: 17524796 | S13: 24.70871
A14: IT | B14: 3161745 | C14: 2887773 | D14: 2.041842 | E14: 3159514 | F14: 3068914 | G14: 4.0870414 | H14: 2846447 | I14: 2555625 | J14: 0.20942037 | K14: 5807854.8 | L14: 5487095 | M14: 2.156684 | N14: 3190206 | O14: 3105275 | P14: 2.6062898 | Q14: 18165767 | R14: 17104682 | S14: 11.101278
A15: Sales | B15: 3083219 | C15: 2844663 | D15: 1.9732595 | E15: 2903436 | F15: 2810895 | G15: 4.1368957 | H15: 2878702 | I15: 2888374 | J15: 4.2568769 | K15: 5046892.2 | L15: 5561752 | M15: 7.8224976 | N15: 3213558 | O15: 3194265 | P15: 2.4390929 | Q15: 17125807 | R15: 17299949 | S15: 20.628623
A16: US | B16: 12245610 | C16: 12199902 | D16: 18.486366 | E16: 12290633 | F16: 12458154 | G16: 15.840386 | H16: 11865216 | I16: 12401531 | J16: 18.79656 | K16: 21615662 | L16: 21315573 | M16: 11.189691 | N16: 11952944 | O16: 12922539 | P16: 23.167335 | Q16: 69970065 | R16: 71297699 | S16: 87.480338
A17: Finance | B17: 3226716 | C17: 2833429 | D17: 2.779211 | E17: 3143225 | F17: 2909543 | G17: 3.4047614 | H17: 2760900 | I17: 3059308 | J17: 6.4351322 | K17: 5832140.4 | L17: 5524846 | M17: 2.7739371 | N17: 2762926 | O17: 3049476 | P17: 7.3415168 | Q17: 17725907 | R17: 17376602 | S17: 22.734558
... A21: Grand Total | B21: 37164605 | C21: 35930274 | D21: 37.616849 | E21: 36053886 | F21: 36756306 | G21: 53.346851 | H21: 35524505 | I21: 36814754 | J21: 56.979829 | K21: 64650181 | L21: 65382207 | M21: 48.280894 | N21: 36976062 | O21: 38231126 | P21: 55.744235 | Q21: 2.1036924e+08 | R21: 213114667 | S21: 251.96866

Sheet YTD Actual by Department
A1: Year | B1: (All)
A2: Entity | B2: (All)
A4: Sum of Actual_Amount | B4: Column Labels
A5: Row Labels | B5: 1 | C5: 2 | D5: 3 | E5: 4 | F5: 5 | G5: 6 | H5: 7 | I5: 8 | J5: 9 | K5: 10 | L5: 11 | M5: 12 | N5: Grand Total
A6: Finance | B6: 4715924 | C6: 8711498 | D6: 13244085 | E6: 18252982 | F6: 22428200 | G6: 27080815 | H6: 31091706 | I6: 35606587 | J6: 39660037 | K6: 44085888 | L6: 48983909 | M6: 53066060
A7: HR | B7: 4287899 | C7: 8589122 | D7: 13125573 | E7: 17373671 | F7: 21835006 | G7: 26221760 | H7: 30561126 | I7: 34629630 | J7: 39276534 | K7: 44020455 | L7: 48712421 | M7: 53142098
A8: IT | B8: 4286903 | C8: 9130007 | D8: 13476202 | E8: 17571003 | F8: 22018771 | G8: 26814817 | H8: 31391052 | I8: 35590969 | J8: 39864673 | K8: 44513457 | L8: 48768547 | M8: 53485783
A9: Sales | B9: 4509818 | C9: 9952093 | D9: 14449561 | E9: 18574877 | F9: 22523806 | G9: 27072850 | H9: 31530040 | I9: 36192876 | J9: 40307690 | K9: 44307724 | L9: 49198156 | M9: 53420726
A10: Grand Total | B10: 17800544 | C10: 36382720 | D10: 54295421 | E10: 71772533 | F10: 88805783 | G10: 107190242 | H10: 124573924 | I10: 142020062 | J10: 159108934 | K10: 176927524 | L10: 195663033 | M10: 213114667
